{
  "code": [
    "301373"
  ],
  "name": "凌玮科技",
  "exchange": [
    "CN"
  ],
  "description": "公司是国内消光用二氧化硅领域龙头企业，亚太地区市占率前三。主营纳米二氧化硅新材料的研发、生产与销售，产品涵盖消光剂、吸附剂、开口剂、防锈颜料、硅溶胶等中高端产品。2025年营收5.00亿元（+4.46%），归母净利润1.37亿元（+1.75%），纳米新材料营收4.82亿元（占比96.42%），毛利率44.96%。2026年1月收购江苏辉迈70%股权，切入化学法球形硅微粉高端电子材料赛道。",
  "remarks": [],
  "concepts": [
    {
      "name": "纳米二氧化硅",
      "reasons": [
        "公司专注于纳米二氧化硅新材料的研发、生产与销售，产品涵盖消光剂、吸附剂、开口剂、防锈颜料、硅溶胶、水性环氧乳液等中高端产品",
        "纳米新材料业务2025年营收4.82亿元（占比96.42%），毛利率持续维持45%+行业高位，主业集中度高、盈利能力强",
        "公司产品广泛应用于涂料、油墨、塑料、石化、光伏、3C电子、轨道交通等20多个应用领域，立足中高端市场持续推进国产替代",
        "公司纳米二氧化硅产品应用于太阳能电池涂覆背板膜，终端客户覆盖光伏领域，已形成稳定收入"
      ]
    },
    {
      "name": "气凝胶",
      "reasons": [
        "公司募投项目'新增2万吨超细二氧化硅气凝胶系列产品项目'已投产，是国内纳米二氧化硅气凝胶领域产能较大、布局较广的企业之一",
        "公司牵头组建湖南省大孔容二氧化硅气凝胶新材料工程技术研究中心，具备自主知识产权的气凝胶产品已实现产业化",
        "公司气凝胶产品广泛应用于新能源保温、涂料、医药载体等领域，随着产能释放有望成为公司长期增长新引擎"
      ]
    },
    {
      "name": "球形硅",
      "reasons": [
        "2026年1月公司以5020万元收购江苏辉迈70%股权，切入化学法球形硅微粉领域，布局高端电子材料新赛道",
        "江苏辉迈是国内少数实现高纯超细亚微米球形硅微粉产业化制备的企业，拥有自主知识产权，纯度达99.99%+",
        "公司球形硅微粉产品可应用于M9级别覆铜板、IC载板、先进封装等AI算力核心领域，已进入下游客户小试阶段"
      ]
    }
  ]
}
