{
  "codes": [
    {
      "region": "CN",
      "code": "300346"
    }
  ],
  "name": "南大光电",
  "description": "国内领先的电子材料供应商，专注先进前驱体（含MO源）、电子特气和光刻胶三大核心半导体材料的研发、生产和销售。产品广泛应用于集成电路、平板显示、LED、第三代半导体、光伏等领域。2025年营收25.85亿元（+9.93%），归母净利润3.20亿元（+18.00%），电子特气收入15.36亿元为最大业务板块。",
  "remarks": [],
  "concepts": [
    {
      "name": "半导体材料",
      "reasons": [
        "三大核心业务（前驱体、电子特气、光刻胶）全部聚焦半导体材料，产品覆盖集成电路全制造环节",
        "2025年光刻胶业务收入突破2000万元，三款ArF光刻胶通过客户验证并取得订单，销售收入同比增长100%",
        "拥有领先的合成、纯化、分析检测和安全储运技术体系，多项产品达到国际先进水平并实现进口替代"
      ]
    },
    {
      "name": "电子特气",
      "reasons": [
        "2025年特气产品收入15.36亿元同比增长1.94%，占总营收59.39%，为收入规模最大的业务板块",
        "氟类气体包括三氟化氮、六氟化硫等，产能和品质国内领先，是国内集成电路及平板显示领域的重要供应商",
        "氢类特气包括高纯磷烷、高纯砷烷、安全源磷烷、安全源砷烷、安全源三氟化硼等，在集成电路行业认可度高，离子注入安全源产品市场份额持续增长"
      ]
    },
    {
      "name": "前驱体",
      "reasons": [
        "2025年前驱体材料（含MO源）收入7.14亿元同比增长23.46%，毛利率达50.88%，为盈利能力最强的业务板块",
        "产品包括ALD/CVD前驱体、高K前驱体/低K前驱体、金属前驱体等，实现了晶圆制造所需主要品类全覆盖",
        "成功导入国内领先芯片制造企业量产制程，成为国内主要的核心前驱体材料供应商之一"
      ]
    },
    {
      "name": "光刻胶",
      "reasons": [
        "2025年光刻胶业务收入突破2000万元，销售收入同比增长100%，三款ArF光刻胶通过客户验证并取得订单",
        "ArF光刻胶已有三款产品通过客户验证，标志着公司在高端光刻胶领域取得实质性突破，有望进入快速放量阶段",
        "作为半导体核心材料的关键布局，光刻胶业务与公司前驱体、电子特气业务形成协同，完善集成电路材料整体解决方案"
      ]
    }
  ]
}
