{
  "codes": [
    {
      "region": "TW",
      "code": "2330"
    },
    {
      "region": "US",
      "code": "TSM"
    }
  ],
  "name": "台积电",
  "alias": [
    "TSM",
    "Taiwan Semiconductor Manufacturing"
  ],
  "description": "Taiwan Semiconductor Manufacturing Company Limited，全球最大的专业集成电路晶圆代工厂，先进制程+先进封装+特殊制程三大技术平台。核心产品涵盖先进制程晶圆（3nm/5nm/2nm）、先进封装（CoWoS/InFO/3D Fabric）、成熟制程晶圆（28nm及以上）等。2025财年营收1224.2亿美元（+35.9%），毛利率59.9%（+3.8pp），营业利润率50.8%，净利552.1亿美元（+51.2%），EPS NT$66.25（+46.4%）。HPC平台营收占58%（+48%），智能手机占29%。3nm制程占晶圆营收24%，5nm占35%，7nm占14%，先进制程（7nm及以下）合计占74%。2nm（N2）于2025年Q4成功量产，N2P和A16计划2026年下半年量产。2026年营收指引增长近30%，长期营收CAGR（2024-2029）接近25%。全年资本支出409亿美元，运营现金流2.3兆新台币。",
  "remarks": [],
  "concepts": [
    {
      "name": "晶圆代工",
      "reasons": [
        "全球最大的专业集成电路晶圆代工厂，2025财年营收1224亿美元（+36%），全球晶圆代工市场份额超60%，稳居行业第一",
        "提供从成熟制程（28nm及以上）到先进制程（3nm/5nm/2nm）的全节点晶圆制造服务，部署305种工艺技术、服务534家客户",
        "Foundry 2.0平台涵盖晶圆制造、先进封装、光掩模等全方位半导体制造服务，2024-2029年营收CAGR目标接近25%"
      ]
    },
    {
      "name": "先进制程",
      "reasons": [
        "全球先进制程晶圆代工绝对龙头，3nm/5nm/7nm制程占晶圆营收74%，服务NVIDIA、AMD、Apple、Qualcomm等全球顶级芯片设计公司",
        "3nm制程第三年大规模量产，2025年占晶圆营收24%；2nm（N2）于2025年Q4成功进入量产，良率良好",
        "2025财年营收1224亿美元（+36%），HPC平台营收占58%（+48%），AI芯片需求为先进制程核心增长驱动力"
      ]
    },
    {
      "name": "先进封装",
      "reasons": [
        "CoWoS（Chip-on-Wafer-on-Substrate）先进封装是AI GPU/HPC芯片不可或缺的关键配套技术，产能供不应求持续扩产",
        "InFO（Integrated Fan-Out）和3D Fabric平台为智能手机和HPC提供异构集成方案，3D IC封装技术行业领先",
        "先进封装与先进制程形成完整的技术平台闭环，是AI芯片从晶圆制造到封装交付的核心枢纽"
      ]
    },
    {
      "name": "成熟制程",
      "reasons": [
        "提供28nm及以上成熟制程晶圆代工服务，2025年占晶圆营收26%，覆盖IoT、汽车电子、消费电子等广泛应用",
        "在日本熊本、德国德累斯顿建设特殊制程晶圆厂，服务全球汽车和工业客户需求，全球化产能布局持续推进",
        "部署305种工艺技术、服务534家客户、制造12682种产品，成熟制程产品组合覆盖范围全球最广"
      ]
    },
    {
      "name": "逻辑芯片代工",
      "reasons": [
        "核心代工业务为逻辑芯片（Logic/SoC）制造，覆盖从0.18μm到3nm/2nm全节点逻辑制程，2025年逻辑制程代工收入占晶圆营收绝大部分",
        "N3 3nm制程第三年大规模量产占晶圆营收24%，N5 5nm占35%，N7 7nm占14%，先进制程（7nm及以下）合计占晶圆营收74%",
        "N2（2nm）于2025年Q4成功量产采用纳米片晶体管，N2P和A16计划2026年下半年量产，A14预计2028年量产引领全球逻辑代工"
      ]
    },
    {
      "name": "射频芯片代工",
      "reasons": [
        "混合信号/射频（MS/RF）为TSMC核心特殊制程平台，提供从成熟RF CMOS到先进N6RF/N4RF的完整射频代工方案，覆盖5G/6G智能手机射频前端、WiFi 7、蓝牙等无线通信芯片",
        "N6RF相比16FFC RF提升3.2倍逻辑密度、降低55%功耗；40RFSOI为射频前端模组集成理想方案；16FFC RF率先进入5G移动网络芯片量产",
        "RF技术持续向先进节点推进以应对sub-6GHz和毫米波频谱需求，TSMC提供RFCMOS和RF-SOI全面覆盖射频收发器和前端模组代工，为全球射频芯片设计公司核心代工伙伴"
      ]
    },
    {
      "name": "电源管理芯片代工",
      "reasons": [
        "BCD（Bipolar-CMOS-DMOS）功率管理工艺为TSMC核心特殊制程，提供从130nm到22nm最完整的BCD代工平台，覆盖电源管理IC/快充/USB接口/音频放大器等应用",
        "40BCD和22BCD面向高数字含量的PMIC应用，逻辑与CMOS基线完全兼容最大化IP复用；55BCD在5V LDMOS领域拥有世界领先性能；130BCD已通过车规认证",
        "正开发全球最先进的22nm BCD平台，服务新能源汽车/服务器等高端市场；BCD+eFlash集成方案面向IoT和可穿戴设备，TSMC在BCD代工领域技术领先于所有纯晶圆代工厂"
      ]
    },
    {
      "name": "嵌入式存储芯片代工",
      "reasons": [
        "嵌入式非易失性存储器（eNVM）为TSMC核心特殊制程，提供代工领域最先进的eFlash/MRAM/RRAM/OTP/MTP全品类嵌入式存储代工方案",
        "eFlash从0.5μm到40nm覆盖消费/工业/车规，40nm车规eFlash 2018年量产，28nm eFlash面向汽车MCU；22ULL嵌入式MRAM全球率先量产并获车规Grade-1认证",
        "28ULL和22ULL嵌入式RRAM第二代方案已进入第三年量产并通过AEC-Q100车规验证；12FFC+嵌入式RRAM第三代方案已进入消费级风险量产"
      ]
    },
    {
      "name": "图像传感器芯片代工",
      "reasons": [
        "CMOS图像传感器（CIS）为TSMC核心特殊制程，提供代工领域最全面的CIS工艺技术组合，覆盖从0.5μm到12nm全节点CIS代工",
        "CIS代工支持手机摄像头/车载影像系统/安防监控/ARVR/医疗影像等多领域，55nm全流程堆栈式CIS、28nm CIS等工艺持续迭代",
        "TSMC CIS技术覆盖BSI/FSI/堆栈式等结构，NIR增强和高动态范围技术领先，为全球CIS芯片设计公司如Sony等的核心代工伙伴"
      ]
    },
    {
      "name": "MEMS传感器芯片代工",
      "reasons": [
        "MEMS（微机电系统）为TSMC核心特殊制程平台，2011年首创Sensor SoC工艺实现MEMS器件与CMOS逻辑单片集成，代工领域技术最领先",
        "MEMS工艺覆盖加速度计/陀螺仪/麦克风/压力传感器/微镜等器件类型，MEMS+CMOS集成方案大幅缩小体积和功耗，适合高端可穿戴/导航等场景",
        "TSMC MEMS代工服务于全球一线MEMS芯片设计公司，率先实现MEMS晶圆堆叠（wafer stacking）技术，在IoT/智能手机/汽车/医疗领域广泛应用"
      ]
    },
    {
      "name": "显示驱动芯片代工",
      "reasons": [
        "高压（HV）制程为TSMC核心特殊制程平台，从0.5μm到28nm全面覆盖显示驱动IC代工，为OLED/LCD/Micro Display等面板驱动芯片提供制造方案",
        "28HV广泛应用于智能手机OLED驱动IC；新推出16HV FinFET高压平台为OLED和Micro Display专用，相较高阶智能手机驱动IC降低35%功耗",
        "N16HV为AI眼鏡缩小40%显示面积并降低26%功耗；TSMC在高压显示驱动代工领域拥有行业最广泛的工艺节点和客户基础"
      ]
    },
    {
      "name": "模拟芯片代工",
      "reasons": [
        "模拟（Analog）/混合信号工艺为TSMC特色制程重要组成部分，提供涵盖高精度模拟/混合信号/数据转换器等芯片代工服务",
        "模拟工艺平台与BCD/RF/CIS等特殊制程形成高度协同，在车规/工业/消费电子等领域广泛应用，支持客户定制化模拟器件需求",
        "TSMC提供全面的模拟制程设计套件（PDK）和IP生态，客户涵盖全球领先的模拟芯片设计公司，模拟代工技术成熟度与广度代工领域领先"
      ]
    },
    {
      "name": "HPC芯片代工",
      "reasons": [
        "HPC（高性能计算）为TSMC第一大营收平台，FY2025占营收58%（+48%），是AI GPU/CPU/NPU/数据中心加速器等芯片的核心代工伙伴",
        "NVIDIA/AMD/Intel等全球顶级HPC芯片设计公司均由TSMC先进制程代工，AI GPU（如Blackwell/GB300等）采用CoWoS先进封装+先进制程一体化方案",
        "HPC需求驱动3nm/5nm产能利用率持续满载，N2面向AI/HPC应用设计定案数达N5同期4倍，A14/A16等未来节点持续为HPC优化PPA"
      ]
    }
  ]
}
