{
  "codes": [
    {
      "region": "US",
      "code": "DELL"
    }
  ],
  "name": "戴尔科技",
  "alias": [],
  "description": "戴尔科技是全球领先的端到端IT基础设施与解决方案提供商，专注于为数据与AI时代提供广泛的创新技术解决方案。公司通过两大业务板块运营：基础设施解决方案集团（ISG）和客户解决方案集团（CSG）。ISG提供AI优化服务器、传统服务器、存储设备（PowerStore/PowerMax/PowerScale）、网络交换机等数据中心全栈基础设施，以及APEX按需付费服务模式。CSG提供商用及消费级PC（笔记本/台式机/工作站）、Alienware游戏设备、显示器等外设产品，以及配置、部署和支持服务。公司业务覆盖全球170多个国家，总部位于美国德克萨斯州朗德罗克。",
  "remarks": [],
  "concepts": [
    {
      "name": "服务器",
      "reasons": [
        "ISG核心产品线，涵盖PowerEdge系列传统服务器及AI优化服务器，x86服务器全球市场份额17.1%",
        "传统服务器提供高可靠通用计算能力，覆盖企业级到数据中心全场景",
        "面向大型企业、公有云厂商及中小企业客户，支持多云和本地部署",
        "主流服务器市场份额28.3%，为全球前三大x86服务器厂商"
      ]
    },
    {
      "name": "AI服务器",
      "reasons": [
        "公司ISG核心增长引擎，FY2026 AI优化服务器出货252亿美元，FY2027 Q1达161亿美元（+757%）",
        "产品覆盖AI模型训练、微调和推理全场景，支持NVIDIA GPU及多样化AI工作负载",
        "在各大CSP客户中建立核心供应地位，AI服务器订单积压创纪录",
        "与NVIDIA深度合作，率先推出基于最新GPU平台的AI服务器系统"
      ]
    },
    {
      "name": "存储设备",
      "reasons": [
        "ISG核心产品线，FY2026年存储营收持续增长，外部存储市场份额29.9%居全球第一",
        "产品涵盖PowerStore（全闪存）、PowerMax（高端存储）、PowerScale（非结构化数据）等全系列",
        "全闪存阵列份额31.6%、高端存储份额44.5%、HCI份额36.6%，均位列行业第一",
        "覆盖主存储、非结构化数据、数据保护、超融合和软件定义存储等多种架构"
      ]
    },
    {
      "name": "交换机",
      "reasons": [
        "ISG产品线重要组成部分，与服务器和存储形成协同配套的数据中心整体解决方案",
        "产品涵盖数据中心交换机、边缘网络交换机、广域网基础设施及线缆光模块",
        "帮助企业客户数字化转型和基础设施现代化，与PowerEdge服务器深度集成",
        "受益AI数据中心建设带来的高速网络互联需求增长"
      ]
    },
    {
      "name": "个人电脑",
      "reasons": [
        "CSG核心业务，FY2026全年营收510亿美元（+5%），商用PC占CSG收入约88%",
        "产品涵盖Latitude商用笔记本、Inspiron消费笔记本、XPS高端PC及OptiPlex台式机等全系列",
        "全球PC市场份额稳居前三，商用PC领域竞争力尤其突出",
        "AIPC集成端侧AI能力，推动商用和消费PC新一轮换机周期"
      ]
    },
    {
      "name": "工作站",
      "reasons": [
        "CSG产品线重要组成部分，Precision系列工作站面向专业设计和计算场景",
        "覆盖移动工作站和塔式工作站，服务于工程制造、媒体娱乐、科学计算等行业",
        "AI工作站集成高性能GPU，支持本地AI开发和推理工作负载",
        "Dell Pro AI Studio等软件生态为专业用户提供AI开发平台"
      ]
    },
    {
      "name": "游戏设备",
      "reasons": [
        "Alienware（外星人）品牌为全球高端游戏PC领导者，涵盖笔记本、台式机、显示器等全品类",
        "Alienware在高端游戏市场具有强大品牌影响力和忠实用户群体",
        "持续推出搭载最新GPU和CPU的高性能游戏主机，覆盖硬核游戏玩家需求",
        "游戏显示器等外设产品与Alienware主机形成完整游戏生态"
      ]
    },
    {
      "name": "显示器",
      "reasons": [
        "戴尔为全球领先的显示器品牌，市场份额长期位居全球第一",
        "产品涵盖商用办公显示器、高端创作显示器、游戏显示器等全场景覆盖",
        "与戴尔PC产品深度协同，为企业客户提供一站式桌面解决方案",
        "持续推出高分辨率、高刷新率及USB-C Hub等创新功能显示器"
      ]
    }
  ]
}
