{
  "codes": [
    {
      "region": "CN",
      "code": "603005"
    }
  ],
  "name": "晶方科技",
  "description": "全球晶圆级芯片尺寸封装服务的主要提供者与技术引领者，专注于传感器领域先进封装测试。拥有领先的硅通孔（TSV）、晶圆级、Fanout、系统级等多样化封装技术，聚焦以影像传感器（CIS）为代表的传感器市场。通过并购拓展微型光学器件设计制造业务。2025年营收同比增长30.44%，归母扣非净利润同比增长51.60%，车规CIS封装业务快速增长，资产负债率仅约11%。",
  "remarks": [],
  "concepts": [
    {
      "name": "集成电路封装",
      "reasons": [
        "公司为全球晶圆级芯片尺寸封装服务的主要提供者与技术引领者，拥有TSV、晶圆级、Fanout、系统级等先进封装技术",
        "具备8英寸和12英寸晶圆级芯片尺寸封装技术规模量产线，涵盖晶圆级到芯片级一站式综合封装服务",
        "持续优化提升TSV-STACK封装工艺水平，迭代创新A-CSP、I-BGA等创新工艺",
        "持续推进Cavity-Last、TSV-LAST相关工艺开发，拓展MEMS、FILTER等领域量产服务能力"
      ]
    },
    {
      "name": "集成电路测试",
      "reasons": [
        "提供晶圆级CIS芯片测试服务，TSV晶圆级测试技术行业领先",
        "拥有8英寸和12英寸晶圆级芯片尺寸封装测试规模量产线，涵盖晶圆级到芯片级一站式测试服务",
        "车规CIS测试业务快速增长，受益于汽车智能化趋势持续深化"
      ]
    },
    {
      "name": "图像传感器芯片封装",
      "reasons": [
        "公司聚焦以图像传感芯片（CIS）为代表的传感器领域，为全球CIS封装技术引领者与市场龙头",
        "封装产品主要包括CIS芯片，广泛应用于智能手机、安防监控、汽车电子、机器人、AI眼镜等",
        "全球CIS市场2025年出货量预计达89亿颗，至2030年市场将平稳增长到301亿美元",
        "车规CIS领域技术领先优势持续提升，汽车智能化推动车载CIS成为增量主力"
      ]
    },
    {
      "name": "图像传感器芯片测试",
      "reasons": [
        "提供晶圆级CIS芯片测试服务，TSV晶圆级测试技术行业领先",
        "车规CIS测试业务快速增长，受益于汽车智能化趋势持续深化"
      ]
    }
  ]
}
