{
  "codes": [
    {
      "region": "CN",
      "code": "301176"
    }
  ],
  "name": "逸豪新材",
  "description": "专业从事高性能铜箔及下游印制电路板（PCB）的研发、生产和销售。电子电路铜箔产品包括HTE箔、LP箔、Mini-LED用特种铜箔、RTF箔等，规格覆盖9μm至210μm。同时具备铝基覆铜板和PCB生产能力，实现垂直一体化布局。与生益科技、南亚新材、鹏鼎控股、景旺电子、胜宏科技等知名企业建立稳定合作。",
  "remarks": [],
  "concepts": [
    {
      "name": "PCB铜箔",
      "reasons": [
        "2025年电子电路铜箔营收12.32亿元占总收入73.85%，年产1.60万吨，为第一大收入来源",
        "产品涵盖HTE、LP、Mini-LED用特种铜箔、RTF等多系列，规格覆盖9μm至210μm",
        "江西省名牌产品，国家高新技术企业、江西省专精特新中小企业"
      ]
    },
    {
      "name": "PCB",
      "reasons": [
        "2025年PCB营收4.36亿元占总收入26.15%，产品覆盖铝基PCB、双面板、多层板",
        "Mini LED板市场竞争力强，终端覆盖三星电子、TCL、小米、海信等全球知名品牌",
        "铝基PCB客户覆盖LG、三星、格力电器、TCL等，应用于高端显示、汽车照明、LED照明",
        "实现电子电路铜箔→铝基覆铜板→PCB全产业链垂直一体化布局"
      ]
    },
    {
      "name": "覆铜板",
      "reasons": [
        "自主研发高导热、高耐电压、高可靠性的铝基覆铜板基材，年产量244万张",
        "铝基覆铜板自用于铝基PCB生产，融合铜箔生产与绝缘胶配方工艺",
        "铝基覆铜板为公司垂直一体化产业链（铜箔→覆铜板→PCB）的关键中间环节"
      ]
    }
  ]
}
