{
  "name": "服务器",
  "alias": [
    "服务器品牌商"
  ],
  "description": "服务器是为网络环境中的客户端计算机提供计算、存储、网络等服务的专用计算机设备，是数据中心和算力基础设施的核心硬件载体。按架构分为x86服务器、ARM服务器等；按应用场景分为通用服务器、AI服务器（GPU服务器）、存储服务器、边缘服务器等。AI大模型训练和推理需求的爆发推动了AI服务器市场的快速增长，服务器产业涵盖品牌整机厂商、ODM代工厂、主板及部件供应商等环节。",
  "remarks": [],
  "stocks": [
    {
      "name": "超微电脑",
      "reasons": []
    },
    {
      "name": "戴尔科技",
      "reasons": []
    },
    {
      "name": "浪潮信息",
      "reasons": []
    },
    {
      "name": "中科曙光",
      "reasons": []
    },
    {
      "name": "紫光股份",
      "reasons": []
    },
    {
      "name": "神州数码",
      "reasons": []
    },
    {
      "name": "华勤技术",
      "reasons": []
    },
    {
      "name": "烽火通信",
      "reasons": []
    }
  ],
  "related": [
    "数据中心",
    "AI服务器",
    "液冷服务器"
  ]
}
